TgBee/__init__.py
TgBee/bot.py
TgBee/filters.py
TgBee/methods.py
TgBee/types.py
tgbee-1.1.12.dist-info/METADATA
tgbee-1.1.12.dist-info/WHEEL
tgbee-1.1.12.dist-info/top_level.txt
tgbee-1.1.12.dist-info/RECORD
