Metadata-Version: 2.2
Name: TgBee
Version: 1.1.12
Summary: An asynchronous Python Telegram Bot API wrapper
Home-page: https://github.com/x7007x/TgBee
Author: Ahmed Negm
Author-email: a7mednegm.x@gmail.com
Classifier: Development Status :: 3 - Alpha
Classifier: Intended Audience :: Developers
Classifier: License :: OSI Approved :: MIT License
Classifier: Operating System :: OS Independent
Classifier: Programming Language :: Python :: 3
Classifier: Programming Language :: Python :: 3.7
Classifier: Programming Language :: Python :: 3.8
Classifier: Programming Language :: Python :: 3.9
Classifier: Programming Language :: Python :: 3.10
Requires-Python: >=3.7
Requires-Dist: aiohttp>=3.7.4
Requires-Dist: aiofiles
Dynamic: author
Dynamic: author-email
Dynamic: classifier
Dynamic: description
Dynamic: description-content-type
Dynamic: home-page
Dynamic: requires-dist
Dynamic: requires-python
Dynamic: summary
